Nikola-8.3.1.data/data/share/doc/nikola/extending.rst
Nikola-8.3.1.data/data/share/doc/nikola/manual.rst
Nikola-8.3.1.data/data/share/doc/nikola/theming.rst
Nikola-8.3.1.data/data/share/man/man1/nikola.1.gz
nikola/__init__.py
nikola/__main__.py
nikola/conf.py.in
nikola/filters.py
nikola/hierarchy_utils.py
nikola/image_processing.py
nikola/log.py
nikola/metadata_extractors.py
nikola/nikola.py
nikola/plugin_categories.py
nikola/plugin_manager.py
nikola/post.py
nikola/shortcodes.py
nikola/state.py
nikola/utils.py
nikola/winutils.py
nikola/data/symlink-test-link.txt
nikola/data/symlink-test-orig.txt
nikola/data/symlinked.txt
nikola/data/samplesite/README.txt
nikola/data/samplesite/files/favicon.ico
nikola/data/samplesite/files/images/nikola.png
nikola/data/samplesite/galleries/demo/exclude.meta
nikola/data/samplesite/galleries/demo/index.txt
nikola/data/samplesite/galleries/demo/metadata.sample.yml
nikola/data/samplesite/galleries/demo/tesla2_lg.jpg
nikola/data/samplesite/galleries/demo/tesla4_lg.jpg
nikola/data/samplesite/galleries/demo/tesla_conducts_lg.webp
nikola/data/samplesite/galleries/demo/tesla_lightning1_lg.jpg
nikola/data/samplesite/galleries/demo/tesla_lightning2_lg.jpg
nikola/data/samplesite/galleries/demo/tesla_tower1_lg.jpg
nikola/data/samplesite/images/frontispiece.jpg
nikola/data/samplesite/images/illus_001.jpg
nikola/data/samplesite/listings/hello.py
nikola/data/samplesite/pages/1.rst
nikola/data/samplesite/pages/bootstrap-demo.rst
nikola/data/samplesite/pages/charts.rst
nikola/data/samplesite/pages/creating-a-theme.rst
nikola/data/samplesite/pages/dr-nikolas-vendetta.rst
nikola/data/samplesite/pages/extending.rst
nikola/data/samplesite/pages/internals.rst
nikola/data/samplesite/pages/listings-demo.rst
nikola/data/samplesite/pages/manual.rst
nikola/data/samplesite/pages/path_handlers.rst
nikola/data/samplesite/pages/quickref.rst
nikola/data/samplesite/pages/quickstart.rst
nikola/data/samplesite/pages/social_buttons.rst
Nikola-8.3.1.dist-info/AUTHORS.txt
Nikola-8.3.1.dist-info/LICENSE.txt
Nikola-8.3.1.dist-info/METADATA
Nikola-8.3.1.dist-info/WHEEL
Nikola-8.3.1.dist-info/entry_points.txt
Nikola-8.3.1.dist-info/top_level.txt
Nikola-8.3.1.dist-info/RECORD
