Metadata-Version: 2.1
Name: Nikola
Version: 8.3.1
Summary: A modular, fast, simple, static website and blog generator
Home-page: https://getnikola.com/
Author: Roberto Alsina and others
Author-email: ralsina@netmanagers.com.ar
License: MIT
Keywords: website,blog,static
Classifier: Development Status :: 5 - Production/Stable
Classifier: Environment :: Console
Classifier: Environment :: Plugins
Classifier: Environment :: Web Environment
Classifier: Intended Audience :: End Users/Desktop
Classifier: License :: OSI Approved :: MIT License
Classifier: Operating System :: MacOS
Classifier: Operating System :: MacOS :: MacOS X
Classifier: Operating System :: Microsoft :: Windows
Classifier: Operating System :: OS Independent
Classifier: Operating System :: POSIX
Classifier: Operating System :: Unix
Classifier: Programming Language :: Python
Classifier: Programming Language :: Python :: 3.8
Classifier: Programming Language :: Python :: 3.9
Classifier: Programming Language :: Python :: 3.10
Classifier: Programming Language :: Python :: 3.11
Classifier: Programming Language :: Python :: 3.12
Classifier: Topic :: Internet
Classifier: Topic :: Internet :: WWW/HTTP
Classifier: Topic :: Text Processing :: Markup
Requires-Python: >=3.8
License-File: LICENSE.txt
License-File: AUTHORS.txt
Requires-Dist: doit >=0.33.1
Requires-Dist: Pygments >=2.4.2
Requires-Dist: Pillow >=9.1.0
Requires-Dist: python-dateutil >=2.8.2
Requires-Dist: docutils >=0.19
Requires-Dist: mako >=1.0.9
Requires-Dist: Markdown >=3.0
Requires-Dist: unidecode >=0.4.16
Requires-Dist: lxml >=4.5.2
Requires-Dist: PyRSS2Gen >=1.1
Requires-Dist: blinker >=1.3
Requires-Dist: setuptools >=60.0.5
Requires-Dist: natsort >=5.1.0
Requires-Dist: requests >=2.31.0
Requires-Dist: piexif >=1.0.3
Requires-Dist: Babel >=2.12.0
Provides-Extra: extras
Requires-Dist: Jinja2 >=3.1.0 ; extra == 'extras'
Requires-Dist: hsluv >=5.0.0 ; extra == 'extras'
Requires-Dist: pyphen >=0.9.1 ; extra == 'extras'
Requires-Dist: micawber >=0.3.0 ; extra == 'extras'
Requires-Dist: pygal >=2.0.11 ; extra == 'extras'
Requires-Dist: typogrify >=2.0.4 ; extra == 'extras'
Requires-Dist: phpserialize >=1.3 ; extra == 'extras'
Requires-Dist: notebook >=6.0.0 ; extra == 'extras'
Requires-Dist: ipykernel >=6.21.2 ; extra == 'extras'
Requires-Dist: ghp-import >=1.0.0 ; extra == 'extras'
Requires-Dist: aiohttp >=3.8.6 ; extra == 'extras'
Requires-Dist: watchdog >=2.3.0 ; extra == 'extras'
Requires-Dist: ruamel.yaml >=0.15.98 ; extra == 'extras'
Requires-Dist: toml >=0.9.2 ; extra == 'extras'
Requires-Dist: html5lib >=1.0.1 ; extra == 'extras'
Provides-Extra: full
Requires-Dist: Jinja2 >=3.1.0 ; extra == 'full'
Requires-Dist: hsluv >=5.0.0 ; extra == 'full'
Requires-Dist: pyphen >=0.9.1 ; extra == 'full'
Requires-Dist: micawber >=0.3.0 ; extra == 'full'
Requires-Dist: pygal >=2.0.11 ; extra == 'full'
Requires-Dist: typogrify >=2.0.4 ; extra == 'full'
Requires-Dist: phpserialize >=1.3 ; extra == 'full'
Requires-Dist: notebook >=6.0.0 ; extra == 'full'
Requires-Dist: ipykernel >=6.21.2 ; extra == 'full'
Requires-Dist: ghp-import >=1.0.0 ; extra == 'full'
Requires-Dist: aiohttp >=3.8.6 ; extra == 'full'
Requires-Dist: watchdog >=2.3.0 ; extra == 'full'
Requires-Dist: ruamel.yaml >=0.15.98 ; extra == 'full'
Requires-Dist: toml >=0.9.2 ; extra == 'full'
Requires-Dist: html5lib >=1.0.1 ; extra == 'full'
Provides-Extra: tests
Requires-Dist: coverage >=4.5.1 ; extra == 'tests'
Requires-Dist: pytest >=4.3.0 ; extra == 'tests'
Requires-Dist: pytest-cov >=2.6.1 ; extra == 'tests'
Requires-Dist: feedparser >=6.0.10 ; extra == 'tests'
Requires-Dist: freezegun >=0.3.10 ; extra == 'tests'
Requires-Dist: flake8 >=3.7.7 ; extra == 'tests'
